aliaser/__init__.py
aliaser/decorator.py
aliaser/metaclass/__init__.py
aliaser/metaclass/alias.py
aliaser/metaclass/multiton.py
aliaser/mixin.py
aliaser-1.0.0.dev7.dist-info/LICENSE
aliaser-1.0.0.dev7.dist-info/METADATA
aliaser-1.0.0.dev7.dist-info/WHEEL
aliaser-1.0.0.dev7.dist-info/RECORD
