Metadata-Version: 2.3
Name: aliaser
Version: 1.0.0.dev7
Summary: Drop-in mix-in + metaclass that let you declare any number of call-perfect aliases for a method with a single decorator or a runtime helper. No boiler-plate forwarders required.
License: MIT License
Author: Taylor B.
Author-email: t.blackstone@inspyre.tech
Requires-Python: >=3.11
Classifier: Development Status :: 4 - Beta
Classifier: Intended Audience :: Developers
Classifier: License :: OSI Approved :: MIT License
Classifier: Operating System :: OS Independent
Classifier: Programming Language :: Python
Classifier: Programming Language :: Python :: 3
Classifier: Programming Language :: Python :: 3 :: Only
Classifier: Programming Language :: Python :: 3.12
Classifier: Topic :: Software Development :: Libraries :: Python Modules
Classifier: Typing :: Typed
Provides-Extra: docs
Requires-Dist: furo (>=2024.8.6) ; extra == "docs"
Requires-Dist: sphinx (>=8.2.3) ; extra == "docs"
